evidence/Controller.py
evidence/__init__.py
evidence/__main__.py
evidence/model/CEAction.py
evidence/model/Line.py
evidence/model/MEAction.py
evidence/model/__init__.py
evidence/phase/CharacterizeEvidence.py
evidence/phase/MergeEvidence.py
evidence/phase/PrepareEvidence.py
evidence/phase/__init__.py
evidence-2.2.0.dist-info/LICENSE.md
evidence-2.2.0.dist-info/METADATA
evidence-2.2.0.dist-info/WHEEL
evidence-2.2.0.dist-info/entry_points.txt
evidence-2.2.0.dist-info/top_level.txt
evidence-2.2.0.dist-info/RECORD
