Metadata-Version: 2.1
Name: evidence
Version: 2.2.0
Summary: Differential analysis of DFXML idifference2.py output
Home-page: https://github.com/5f0ne/evidence
Author: 5f0
License: MIT
Classifier: Operating System :: OS Independent 
Classifier: Programming Language :: Python :: 3 
Classifier: License :: OSI Approved :: MIT License 
License-File: LICENSE.md
